AppConfiguration.py
mcr_mclib.py
mcLib-0.0.5.dist-info/METADATA
mcLib-0.0.5.dist-info/WHEEL
mcLib-0.0.5.dist-info/top_level.txt
mcLib-0.0.5.dist-info/RECORD
