Metadata-Version: 2.1
Name: mcLib
Version: 0.0.5
Summary: This is just a base package for logging and other handy functions
Home-page: UNKNOWN
Author: Michael Robinson
Author-email: michael.robinson@kochind.com
License: MIT
Platform: UNKNOWN
Requires-Dist: json-minify
Requires-Dist: pandas
Requires-Dist: numpy
